instabot/__init__.py
instabot/utils.py
instabot/api/__init__.py
instabot/api/api.py
instabot/api/api_photo.py
instabot/api/api_video.py
instabot/api/config.py
instabot/api/devices.py
instabot/api/prepare.py
instabot/bot/__init__.py
instabot/bot/bot.py
instabot/bot/bot_archive.py
instabot/bot/bot_block.py
instabot/bot/bot_checkpoint.py
instabot/bot/bot_comment.py
instabot/bot/bot_delete.py
instabot/bot/bot_direct.py
instabot/bot/bot_filter.py
instabot/bot/bot_follow.py
instabot/bot/bot_get.py
instabot/bot/bot_like.py
instabot/bot/bot_photo.py
instabot/bot/bot_stats.py
instabot/bot/bot_support.py
instabot/bot/bot_unfollow.py
instabot/bot/bot_unlike.py
instabot/bot/bot_video.py
instabot-0.5.0.dist-info/LICENSE
instabot-0.5.0.dist-info/METADATA
instabot-0.5.0.dist-info/WHEEL
instabot-0.5.0.dist-info/top_level.txt
instabot-0.5.0.dist-info/RECORD
