Metadata-Version: 2.1
Name: instabot
Version: 0.5.0
Summary: Cool Instagram bot scripts and API python wrapper.
Home-page: https://github.com/instagrambot/instabot
Author: Daniil Okhlopkov, Evgeny Kemerov
Author-email: ohld@icloud.com, eskemerov@gmail.com
License: UNKNOWN
Download-URL: https://github.com/instagrambot/instabot/tarball/0.5.0
Keywords: instagram,bot,api,wrapper
Platform: UNKNOWN
Requires-Dist: tqdm
Requires-Dist: requests-toolbelt
Requires-Dist: requests
Requires-Dist: schedule
Requires-Dist: future
Requires-Dist: six
Requires-Dist: huepy
